cla_check/__init__.py
cla_check/_cla.py
cla_check/_git.py
cla_check/_lp.py
cla_check/_term.py
cla_check/_commands/__init__.py
cla_check/_commands/_cla_check.py
cla_check/_commands/_cla_check_git.py
cla_check-0.3.1.dist-info/LICENSE
cla_check-0.3.1.dist-info/METADATA
cla_check-0.3.1.dist-info/WHEEL
cla_check-0.3.1.dist-info/entry_points.txt
cla_check-0.3.1.dist-info/top_level.txt
cla_check-0.3.1.dist-info/RECORD
